irisml/compiler/__init__.py
irisml/compiler/api.py
irisml/compiler/compiler.py
irisml/compiler/stubs.py
irisml/compiler/commands/compile.py
irisml/core/__init__.py
irisml/core/cache_manager.py
irisml/core/context.py
irisml/core/description.py
irisml/core/hash_generator.py
irisml/core/job.py
irisml/core/job_runner.py
irisml/core/task.py
irisml/core/task_base.py
irisml/core/variable.py
irisml/core/commands/cache.py
irisml/core/commands/common.py
irisml/core/commands/patch.py
irisml/core/commands/run.py
irisml/core/commands/run_task.py
irisml/core/commands/show.py
irisml/test/__init__.py
irisml/test/generate.py
irisml-0.0.38.dist-info/LICENSE
irisml-0.0.38.dist-info/METADATA
irisml-0.0.38.dist-info/WHEEL
irisml-0.0.38.dist-info/entry_points.txt
irisml-0.0.38.dist-info/top_level.txt
irisml-0.0.38.dist-info/RECORD
