Metadata-Version: 2.1
Name: irisml
Version: 0.0.38
Summary: Simple ML pipeline platform
Home-page: https://github.com/microsoft/irisml
Author: irisdev
License: MIT
Requires-Python: >=3.8
License-File: LICENSE
Requires-Dist: azure-identity
Requires-Dist: azure-storage-blob <13
Requires-Dist: numpy
Requires-Dist: tenacity
Requires-Dist: torch
